trainloop_llm_logging/__init__.py
trainloop_llm_logging/config.py
trainloop_llm_logging/exporter.py
trainloop_llm_logging/instrumentation/__init__.py
trainloop_llm_logging/instrumentation/http_client_lib.py
trainloop_llm_logging/instrumentation/httpx_lib.py
trainloop_llm_logging/instrumentation/requests_lib.py
trainloop_llm_logging/instrumentation/utils.py
trainloop_llm_logging/logger.py
trainloop_llm_logging/register.py
trainloop_llm_logging/store.py
trainloop_llm_logging/types.py
trainloop_llm_logging-0.8.0.dist-info/METADATA
trainloop_llm_logging-0.8.0.dist-info/WHEEL
trainloop_llm_logging-0.8.0.dist-info/RECORD
