Metadata-Version: 2.3
Name: trainloop-llm-logging
Version: 0.8.0
Summary: TrainLoop LLM Logging SDK for data collection
Author: Mason Pierce
Author-email: masonpierce@trainloop.ai
Requires-Python: >=3.11,<4.0
Classifier: Programming Language :: Python :: 3
Classifier: Programming Language :: Python :: 3.11
Classifier: Programming Language :: Python :: 3.12
Classifier: Programming Language :: Python :: 3.13
Requires-Dist: fsspec (>=2023.1.0)
Requires-Dist: pyyaml (>=6.0,<7.0)
Requires-Dist: requests (>=2.31.0,<3.0.0)
